fsclean/__init__.py
fsclean/__main__.py
fsclean-1.0.0.dist-info/entry_points.txt
fsclean-1.0.0.dist-info/LICENSE
fsclean-1.0.0.dist-info/WHEEL
fsclean-1.0.0.dist-info/METADATA
fsclean-1.0.0.dist-info/RECORD
